colour_palette_gen/__init__.py
colour_palette_gen/generate.py
Color_Palette_Generator-0.0.4.dist-info/LICENSE
Color_Palette_Generator-0.0.4.dist-info/METADATA
Color_Palette_Generator-0.0.4.dist-info/WHEEL
Color_Palette_Generator-0.0.4.dist-info/top_level.txt
Color_Palette_Generator-0.0.4.dist-info/RECORD
